{
	"info": {
		"_postman_id": "080f0693-d954-4b62-9735-e4f9b8872d8e",
		"name": "Trello",
		"schema": "https://schema.getpostman.com/json/collection/v2.1.0/collection.json",
		"_exporter_id": "23133550"
	},
	"item": [
		{
			"name": "createOrganization",
			"event": [
				{
					"listen": "test",
					"script": {
						"exec": [
							"var jsonData = JSON.parse(responseBody);\r",
							"pm.environment.set(\"organization_id\", jsonData.id);\r",
							"pm.test(\"Status code is 200\", function () {\r",
							"    pm.response.to.have.status(200);\r",
							"});"
						],
						"type": "text/javascript"
					}
				}
			],
			"protocolProfileBehavior": {
				"disabledSystemHeaders": {}
			},
			"request": {
				"auth": {
					"type": "oauth1",
					"oauth1": [
						{
							"key": "addParamsToHeader",
							"value": true,
							"type": "boolean"
						},
						{
							"key": "token",
							"value": "ATTA4e6e99839c3abeb48f52269d64165e8316da6700694a57a690443f3a1f2386bc1BFEFE43\n",
							"type": "string"
						},
						{
							"key": "consumerSecret",
							"value": "ae949d9395642e68d0b86f82e62e680d6900760f2f2759f46ab7d5a1397bc750",
							"type": "string"
						},
						{
							"key": "consumerKey",
							"value": "619f90d1bc8888d5d70628ed26cae824",
							"type": "string"
						},
						{
							"key": "signatureMethod",
							"value": "HMAC-SHA1",
							"type": "string"
						},
						{
							"key": "version",
							"value": "1.0",
							"type": "string"
						},
						{
							"key": "addEmptyParamsToSign",
							"value": false,
							"type": "boolean"
						}
					]
				},
				"method": "POST",
				"header": [
					{
						"key": "Accept",
						"value": "application/json",
						"type": "text"
					}
				],
				"body": {
					"mode": "raw",
					"raw": "",
					"options": {
						"raw": {
							"language": "text"
						}
					}
				},
				"url": {
					"raw": "{{BaseURL}}/1/organizations?displayName=Organization&key={{key}}&token={{Token}}",
					"host": [
						"{{BaseURL}}"
					],
					"path": [
						"1",
						"organizations"
					],
					"query": [
						{
							"key": "displayName",
							"value": "Organization"
						},
						{
							"key": "key",
							"value": "{{key}}"
						},
						{
							"key": "token",
							"value": "{{Token}}"
						}
					]
				}
			},
			"response": []
		},
		{
			"name": "getOrganizationForMember",
			"event": [
				{
					"listen": "test",
					"script": {
						"exec": [
							"var jsonData = JSON.parse(responseBody);\r",
							"pm.environment.set(\"member_id\", jsonData.id);\r",
							"pm.test(\"Status code is 200\", function () {\r",
							"    pm.response.to.have.status(200);\r",
							"});"
						],
						"type": "text/javascript"
					}
				}
			],
			"request": {
				"auth": {
					"type": "oauth1",
					"oauth1": [
						{
							"key": "addParamsToHeader",
							"value": true,
							"type": "boolean"
						},
						{
							"key": "token",
							"value": "ATTA4e6e99839c3abeb48f52269d64165e8316da6700694a57a690443f3a1f2386bc1BFEFE43\n",
							"type": "string"
						},
						{
							"key": "consumerSecret",
							"value": "ae949d9395642e68d0b86f82e62e680d6900760f2f2759f46ab7d5a1397bc750",
							"type": "string"
						},
						{
							"key": "consumerKey",
							"value": "619f90d1bc8888d5d70628ed26cae824",
							"type": "string"
						},
						{
							"key": "signatureMethod",
							"value": "HMAC-SHA1",
							"type": "string"
						},
						{
							"key": "version",
							"value": "1.0",
							"type": "string"
						},
						{
							"key": "addEmptyParamsToSign",
							"value": false,
							"type": "boolean"
						}
					]
				},
				"method": "GET",
				"header": [],
				"url": {
					"raw": "https://api.trello.com/1/members/me?key={{key}}&token={{token}}",
					"protocol": "https",
					"host": [
						"api",
						"trello",
						"com"
					],
					"path": [
						"1",
						"members",
						"me"
					],
					"query": [
						{
							"key": "key",
							"value": "{{key}}"
						},
						{
							"key": "token",
							"value": "{{token}}"
						}
					]
				}
			},
			"response": []
		},
		{
			"name": "createBoardInsideOrganization",
			"event": [
				{
					"listen": "test",
					"script": {
						"exec": [
							"var jsonData = JSON.parse(responseBody);\r",
							"pm.environment.set(\"board_id\", jsonData.id);\r",
							"pm.test(\"Status code is 200\", function () {\r",
							"    pm.response.to.have.status(200);\r",
							"});"
						],
						"type": "text/javascript"
					}
				}
			],
			"request": {
				"auth": {
					"type": "oauth1",
					"oauth1": [
						{
							"key": "addParamsToHeader",
							"value": true,
							"type": "boolean"
						},
						{
							"key": "token",
							"value": "ATTA4e6e99839c3abeb48f52269d64165e8316da6700694a57a690443f3a1f2386bc1BFEFE43\n",
							"type": "string"
						},
						{
							"key": "consumerSecret",
							"value": "ae949d9395642e68d0b86f82e62e680d6900760f2f2759f46ab7d5a1397bc750",
							"type": "string"
						},
						{
							"key": "consumerKey",
							"value": "619f90d1bc8888d5d70628ed26cae824",
							"type": "string"
						},
						{
							"key": "signatureMethod",
							"value": "HMAC-SHA1",
							"type": "string"
						},
						{
							"key": "version",
							"value": "1.0",
							"type": "string"
						},
						{
							"key": "addEmptyParamsToSign",
							"value": false,
							"type": "boolean"
						}
					]
				},
				"method": "POST",
				"header": [],
				"url": {
					"raw": "https://api.trello.com/1/boards/?name=EgFwd2&key={{key}}&token={{Token}}",
					"protocol": "https",
					"host": [
						"api",
						"trello",
						"com"
					],
					"path": [
						"1",
						"boards",
						""
					],
					"query": [
						{
							"key": "name",
							"value": "EgFwd2"
						},
						{
							"key": "key",
							"value": "{{key}}"
						},
						{
							"key": "token",
							"value": "{{Token}}"
						}
					]
				}
			},
			"response": []
		},
		{
			"name": "getOrganizationBoards",
			"event": [
				{
					"listen": "test",
					"script": {
						"exec": [
							"pm.test(\"Status code is 200\", function () {\r",
							"    pm.response.to.have.status(200);\r",
							"});"
						],
						"type": "text/javascript"
					}
				}
			],
			"request": {
				"auth": {
					"type": "oauth1",
					"oauth1": [
						{
							"key": "addParamsToHeader",
							"value": true,
							"type": "boolean"
						},
						{
							"key": "token",
							"value": "ATTA4e6e99839c3abeb48f52269d64165e8316da6700694a57a690443f3a1f2386bc1BFEFE43\n",
							"type": "string"
						},
						{
							"key": "consumerSecret",
							"value": "ae949d9395642e68d0b86f82e62e680d6900760f2f2759f46ab7d5a1397bc750",
							"type": "string"
						},
						{
							"key": "consumerKey",
							"value": "619f90d1bc8888d5d70628ed26cae824",
							"type": "string"
						},
						{
							"key": "signatureMethod",
							"value": "HMAC-SHA1",
							"type": "string"
						},
						{
							"key": "version",
							"value": "1.0",
							"type": "string"
						},
						{
							"key": "addEmptyParamsToSign",
							"value": false,
							"type": "boolean"
						}
					]
				},
				"method": "GET",
				"header": [],
				"url": {
					"raw": "https://api.trello.com/1/organizations/{{organization_id}}/boards/?key={{key}}&token={{Token}}",
					"protocol": "https",
					"host": [
						"api",
						"trello",
						"com"
					],
					"path": [
						"1",
						"organizations",
						"{{organization_id}}",
						"boards",
						""
					],
					"query": [
						{
							"key": "key",
							"value": "{{key}}"
						},
						{
							"key": "token",
							"value": "{{Token}}"
						}
					]
				}
			},
			"response": []
		},
		{
			"name": "createListInSpecificBoard",
			"event": [
				{
					"listen": "test",
					"script": {
						"exec": [
							"var jsonData = JSON.parse(responseBody);\r",
							"pm.environment.set(\"list_id\", jsonData.id);\r",
							"pm.test(\"Status code is 200\", function () {\r",
							"    pm.response.to.have.status(200);\r",
							"});"
						],
						"type": "text/javascript"
					}
				}
			],
			"request": {
				"auth": {
					"type": "oauth1",
					"oauth1": [
						{
							"key": "addParamsToHeader",
							"value": true,
							"type": "boolean"
						},
						{
							"key": "token",
							"value": "ATTA4e6e99839c3abeb48f52269d64165e8316da6700694a57a690443f3a1f2386bc1BFEFE43\n",
							"type": "string"
						},
						{
							"key": "consumerSecret",
							"value": "ae949d9395642e68d0b86f82e62e680d6900760f2f2759f46ab7d5a1397bc750",
							"type": "string"
						},
						{
							"key": "consumerKey",
							"value": "619f90d1bc8888d5d70628ed26cae824",
							"type": "string"
						},
						{
							"key": "signatureMethod",
							"value": "HMAC-SHA1",
							"type": "string"
						},
						{
							"key": "version",
							"value": "1.0",
							"type": "string"
						},
						{
							"key": "addEmptyParamsToSign",
							"value": false,
							"type": "boolean"
						}
					]
				},
				"method": "POST",
				"header": [],
				"url": {
					"raw": "https://api.trello.com/1/lists?name=front end Testing&idBoard={{board_id}}&key={{key}}&token={{Token}}",
					"protocol": "https",
					"host": [
						"api",
						"trello",
						"com"
					],
					"path": [
						"1",
						"lists"
					],
					"query": [
						{
							"key": "name",
							"value": "front end Testing"
						},
						{
							"key": "idBoard",
							"value": "{{board_id}}"
						},
						{
							"key": "key",
							"value": "{{key}}"
						},
						{
							"key": "token",
							"value": "{{Token}}"
						}
					]
				}
			},
			"response": []
		},
		{
			"name": "getListsInBoard",
			"event": [
				{
					"listen": "test",
					"script": {
						"exec": [
							"pm.test(\"Status code is 200\", function () {\r",
							"    pm.response.to.have.status(200);\r",
							"});"
						],
						"type": "text/javascript"
					}
				}
			],
			"request": {
				"auth": {
					"type": "oauth1",
					"oauth1": [
						{
							"key": "addParamsToHeader",
							"value": true,
							"type": "boolean"
						},
						{
							"key": "token",
							"value": "ATTA4e6e99839c3abeb48f52269d64165e8316da6700694a57a690443f3a1f2386bc1BFEFE43\n",
							"type": "string"
						},
						{
							"key": "consumerSecret",
							"value": "ae949d9395642e68d0b86f82e62e680d6900760f2f2759f46ab7d5a1397bc750",
							"type": "string"
						},
						{
							"key": "consumerKey",
							"value": "619f90d1bc8888d5d70628ed26cae824",
							"type": "string"
						},
						{
							"key": "signatureMethod",
							"value": "HMAC-SHA1",
							"type": "string"
						},
						{
							"key": "version",
							"value": "1.0",
							"type": "string"
						},
						{
							"key": "addEmptyParamsToSign",
							"value": false,
							"type": "boolean"
						}
					]
				},
				"method": "GET",
				"header": [],
				"url": {
					"raw": "https://api.trello.com/1/boards/{{board_id}}/lists?key={{key}}&token={{Token}}",
					"protocol": "https",
					"host": [
						"api",
						"trello",
						"com"
					],
					"path": [
						"1",
						"boards",
						"{{board_id}}",
						"lists"
					],
					"query": [
						{
							"key": "key",
							"value": "{{key}}"
						},
						{
							"key": "token",
							"value": "{{Token}}"
						}
					]
				}
			},
			"response": []
		},
		{
			"name": "archiveList",
			"event": [
				{
					"listen": "test",
					"script": {
						"exec": [
							"pm.test(\"Status code is 200\", function () {\r",
							"    pm.response.to.have.status(200);\r",
							"});"
						],
						"type": "text/javascript"
					}
				}
			],
			"request": {
				"auth": {
					"type": "oauth1",
					"oauth1": [
						{
							"key": "addParamsToHeader",
							"value": true,
							"type": "boolean"
						},
						{
							"key": "token",
							"value": "ATTA4e6e99839c3abeb48f52269d64165e8316da6700694a57a690443f3a1f2386bc1BFEFE43\n",
							"type": "string"
						},
						{
							"key": "consumerSecret",
							"value": "ae949d9395642e68d0b86f82e62e680d6900760f2f2759f46ab7d5a1397bc750",
							"type": "string"
						},
						{
							"key": "consumerKey",
							"value": "619f90d1bc8888d5d70628ed26cae824",
							"type": "string"
						},
						{
							"key": "signatureMethod",
							"value": "HMAC-SHA1",
							"type": "string"
						},
						{
							"key": "version",
							"value": "1.0",
							"type": "string"
						},
						{
							"key": "addEmptyParamsToSign",
							"value": false,
							"type": "boolean"
						}
					]
				},
				"method": "PUT",
				"header": [],
				"body": {
					"mode": "raw",
					"raw": "",
					"options": {
						"raw": {
							"language": "json"
						}
					}
				},
				"url": {
					"raw": "https://api.trello.com/1/lists/{{list_id}}/closed?value=true&key={{key}}&token={{Token}}",
					"protocol": "https",
					"host": [
						"api",
						"trello",
						"com"
					],
					"path": [
						"1",
						"lists",
						"{{list_id}}",
						"closed"
					],
					"query": [
						{
							"key": "value",
							"value": "true"
						},
						{
							"key": "key",
							"value": "{{key}}"
						},
						{
							"key": "token",
							"value": "{{Token}}"
						}
					]
				}
			},
			"response": []
		},
		{
			"name": "delete board",
			"event": [
				{
					"listen": "test",
					"script": {
						"exec": [
							"pm.test(\"Status code is 200\", function () {\r",
							"    pm.response.to.have.status(200);\r",
							"});"
						],
						"type": "text/javascript"
					}
				}
			],
			"request": {
				"auth": {
					"type": "oauth1",
					"oauth1": [
						{
							"key": "addParamsToHeader",
							"value": true,
							"type": "boolean"
						},
						{
							"key": "token",
							"value": "ATTA4e6e99839c3abeb48f52269d64165e8316da6700694a57a690443f3a1f2386bc1BFEFE43\n",
							"type": "string"
						},
						{
							"key": "consumerSecret",
							"value": "ae949d9395642e68d0b86f82e62e680d6900760f2f2759f46ab7d5a1397bc750",
							"type": "string"
						},
						{
							"key": "consumerKey",
							"value": "619f90d1bc8888d5d70628ed26cae824",
							"type": "string"
						},
						{
							"key": "signatureMethod",
							"value": "HMAC-SHA1",
							"type": "string"
						},
						{
							"key": "version",
							"value": "1.0",
							"type": "string"
						},
						{
							"key": "addEmptyParamsToSign",
							"value": false,
							"type": "boolean"
						}
					]
				},
				"method": "DELETE",
				"header": [],
				"url": {
					"raw": "{{BaseURL}}/1/boards/{{board_id}}?key={{key}}&token={{Token}}",
					"host": [
						"{{BaseURL}}"
					],
					"path": [
						"1",
						"boards",
						"{{board_id}}"
					],
					"query": [
						{
							"key": "key",
							"value": "{{key}}"
						},
						{
							"key": "token",
							"value": "{{Token}}"
						}
					]
				}
			},
			"response": []
		},
		{
			"name": "deleteOrganization",
			"event": [
				{
					"listen": "test",
					"script": {
						"exec": [
							"pm.test(\"Status code is 200\", function () {\r",
							"    pm.response.to.have.status(200);\r",
							"});"
						],
						"type": "text/javascript"
					}
				}
			],
			"request": {
				"auth": {
					"type": "oauth1",
					"oauth1": [
						{
							"key": "addParamsToHeader",
							"value": true,
							"type": "boolean"
						},
						{
							"key": "token",
							"value": "ATTA4e6e99839c3abeb48f52269d64165e8316da6700694a57a690443f3a1f2386bc1BFEFE43\n",
							"type": "string"
						},
						{
							"key": "consumerSecret",
							"value": "ae949d9395642e68d0b86f82e62e680d6900760f2f2759f46ab7d5a1397bc750",
							"type": "string"
						},
						{
							"key": "consumerKey",
							"value": "619f90d1bc8888d5d70628ed26cae824",
							"type": "string"
						},
						{
							"key": "signatureMethod",
							"value": "HMAC-SHA1",
							"type": "string"
						},
						{
							"key": "version",
							"value": "1.0",
							"type": "string"
						},
						{
							"key": "addEmptyParamsToSign",
							"value": false,
							"type": "boolean"
						}
					]
				},
				"method": "DELETE",
				"header": [],
				"url": {
					"raw": "https://api.trello.com/1/organizations/{{organization_id}}?key={{key}}&token={{Token}}",
					"protocol": "https",
					"host": [
						"api",
						"trello",
						"com"
					],
					"path": [
						"1",
						"organizations",
						"{{organization_id}}"
					],
					"query": [
						{
							"key": "key",
							"value": "{{key}}"
						},
						{
							"key": "token",
							"value": "{{Token}}"
						}
					]
				}
			},
			"response": []
		}
	]
}